codeguard/__init__.py
codeguard/cli.py
alkin_codeguard-0.1.dist-info/METADATA
alkin_codeguard-0.1.dist-info/WHEEL
alkin_codeguard-0.1.dist-info/entry_points.txt
alkin_codeguard-0.1.dist-info/top_level.txt
alkin_codeguard-0.1.dist-info/RECORD
