Metadata-Version: 2.4
Name: alkin-codeguard
Version: 0.1
Requires-Dist: click
Requires-Dist: requests
Requires-Dist: python-dotenv
Dynamic: requires-dist
